monitor_msg_tools/__init__.py
monitor_msg_tools/dingMsg.py
monitor_msg_tools/genhtml.py
monitor_msg_tools/sendEmail.py
monitor_msg_tools-0.0.2.dist-info/METADATA
monitor_msg_tools-0.0.2.dist-info/WHEEL
monitor_msg_tools-0.0.2.dist-info/top_level.txt
monitor_msg_tools-0.0.2.dist-info/RECORD
