Metadata-Version: 2.1
Name: monitor-msg-tools
Version: 0.0.2
Summary: simple tool
Home-page: https://github.com/Nevquit/monitor_msg_tools
Author: vSir
Author-email: weiguo341@gmail.com
License: UNKNOWN
Platform: UNKNOWN
Classifier: Programming Language :: Python :: 3
Classifier: License :: OSI Approved :: MIT License
Classifier: Operating System :: OS Independent
Requires-Dist: pandas
Requires-Dist: requests
